azure/digitaltwins/core/__init__.py
azure/digitaltwins/core/_digitaltwins_client.py
azure/digitaltwins/core/_utils.py
azure/digitaltwins/core/_version.py
azure/digitaltwins/core/py.typed
azure/digitaltwins/core/_generated/__init__.py
azure/digitaltwins/core/_generated/_azure_digital_twins_api.py
azure/digitaltwins/core/_generated/_configuration.py
azure/digitaltwins/core/_generated/_patch.py
azure/digitaltwins/core/_generated/_vendor.py
azure/digitaltwins/core/_generated/_version.py
azure/digitaltwins/core/_generated/aio/__init__.py
azure/digitaltwins/core/_generated/aio/_azure_digital_twins_api.py
azure/digitaltwins/core/_generated/aio/_configuration.py
azure/digitaltwins/core/_generated/aio/_patch.py
azure/digitaltwins/core/_generated/aio/operations/__init__.py
azure/digitaltwins/core/_generated/aio/operations/_digital_twin_models_operations.py
azure/digitaltwins/core/_generated/aio/operations/_digital_twins_operations.py
azure/digitaltwins/core/_generated/aio/operations/_event_routes_operations.py
azure/digitaltwins/core/_generated/aio/operations/_query_operations.py
azure/digitaltwins/core/_generated/models/__init__.py
azure/digitaltwins/core/_generated/models/_models.py
azure/digitaltwins/core/_generated/models/_models_py3.py
azure/digitaltwins/core/_generated/operations/__init__.py
azure/digitaltwins/core/_generated/operations/_digital_twin_models_operations.py
azure/digitaltwins/core/_generated/operations/_digital_twins_operations.py
azure/digitaltwins/core/_generated/operations/_event_routes_operations.py
azure/digitaltwins/core/_generated/operations/_query_operations.py
azure/digitaltwins/core/aio/__init__.py
azure/digitaltwins/core/aio/_digitaltwins_client_async.py
azure_digitaltwins_core-1.2.0.dist-info/LICENSE
azure_digitaltwins_core-1.2.0.dist-info/METADATA
azure_digitaltwins_core-1.2.0.dist-info/WHEEL
azure_digitaltwins_core-1.2.0.dist-info/top_level.txt
azure_digitaltwins_core-1.2.0.dist-info/RECORD
