Metadata-Version: 2.1
Name: azure-digitaltwins-core
Version: 1.2.0
Summary: Microsoft Azure Azure DigitalTwins Core Client Library for Python
Home-page: https://github.com/Azure/azure-sdk-for-python/tree/main/sdk/digitaltwins/azure-digitaltwins-core
Author: Microsoft Corporation
Author-email: azure-digitaltwins-core@microsoft.com
License: MIT License
Platform: UNKNOWN
Classifier: Development Status :: 4 - Beta
Classifier: Programming Language :: Python
Classifier: Programming Language :: Python :: 3 :: Only
Classifier: Programming Language :: Python :: 3.7
Classifier: Programming Language :: Python :: 3.8
Classifier: Programming Language :: Python :: 3.9
Classifier: Programming Language :: Python :: 3.10
Classifier: License :: OSI Approved :: MIT License
Requires-Python: >=3.7
Requires-Dist: azure-core (<2.0.0,>=1.20.0)
Requires-Dist: msrest (>=0.6.21)
